rewact/__init__.py
rewact/dataset_with_reward.py
rewact/py.typed
rewact/utils.py
rewact/policy/__init__.py
rewact/policy/configuration_rewact.py
rewact/policy/modeling_rewact.py
rewact-0.1.4.dist-info/licenses/LICENSE
rewact-0.1.4.dist-info/METADATA
rewact-0.1.4.dist-info/WHEEL
rewact-0.1.4.dist-info/top_level.txt
rewact-0.1.4.dist-info/RECORD
