Metadata-Version: 2.4
Name: rewact
Version: 0.1.4
Summary: RewACT: Reward-Augmented Action Chunking with Transformers
Author: Ville Kuosmanen
License: MIT License
Project-URL: Homepage, https://github.com/villekuosmanen/rewACT
Project-URL: Repository, https://github.com/villekuosmanen/rewACT
Project-URL: Documentation, https://github.com/villekuosmanen/rewACT
Project-URL: Bug Tracker, https://github.com/villekuosmanen/rewACT/issues
Classifier: Development Status :: 3 - Alpha
Classifier: Intended Audience :: Science/Research
Classifier: License :: OSI Approved :: Apache Software License
Classifier: Programming Language :: Python :: 3
Classifier: Programming Language :: Python :: 3.10
Classifier: Programming Language :: Python :: 3.11
Classifier: Topic :: Scientific/Engineering :: Artificial Intelligence
Requires-Python: >=3.10
License-File: LICENSE
Requires-Dist: lerobot
Requires-Dist: einops>=0.6.0
Requires-Dist: scipy>=1.7.0
Provides-Extra: dev
Requires-Dist: pytest>=7.0; extra == "dev"
Requires-Dist: black>=22.0; extra == "dev"
Requires-Dist: isort>=5.0; extra == "dev"
Requires-Dist: flake8>=4.0; extra == "dev"
Requires-Dist: mypy>=0.950; extra == "dev"
Provides-Extra: scripts
Requires-Dist: wandb; extra == "scripts"
Requires-Dist: hydra-core>=1.2.0; extra == "scripts"
Provides-Extra: all
Requires-Dist: pytest>=7.0; extra == "all"
Requires-Dist: black>=22.0; extra == "all"
Requires-Dist: isort>=5.0; extra == "all"
Requires-Dist: flake8>=4.0; extra == "all"
Requires-Dist: mypy>=0.950; extra == "all"
Requires-Dist: wandb; extra == "all"
Requires-Dist: hydra-core>=1.2.0; extra == "all"
Dynamic: license-file
